bibt/slack/__init__.py
bibt/slack/methods.py
bibt/slack/params.py
bibt/slack/version.py
bibt_slack-0.1.4.dist-info/METADATA
bibt_slack-0.1.4.dist-info/WHEEL
bibt_slack-0.1.4.dist-info/licenses/LICENSE
bibt_slack-0.1.4.dist-info/RECORD
