Metadata-Version: 2.3
Name: bibt-slack
Version: 0.1.4
Summary: Functionality often used by BITS Blue Team (Slack).
Project-URL: Bug Tracker, https://github.com/broadinstitute/bibt-slack/issues
Project-URL: Documentation, https://bibt-slack.readthedocs.io/en/latest/
Project-URL: Homepage, https://github.com/broadinstitute/bibt-slack
Author-email: Matthew OBrien <mobrien@broadinstitute.org>
Classifier: License :: OSI Approved :: MIT License
Classifier: Operating System :: OS Independent
Classifier: Programming Language :: Python :: 3
Classifier: Programming Language :: Python :: 3.9
Classifier: Programming Language :: Python :: 3.10
Classifier: Programming Language :: Python :: 3.11
Classifier: Programming Language :: Python :: 3.12
Classifier: Topic :: Security
Classifier: Topic :: Software Development :: Libraries
Classifier: Topic :: Utilities
Requires-Python: >=3.9
Requires-Dist: requests==2.31.0
